[
  {
    "variation": "default",
    "version": "sktwi1xtmkfgx8626",
    "items": [
      {
        "latestPostsTitle": "11111111111",
        "latestPostsText": [
          {
            "type": "paragraph",
            "text": "Consectetur incididunt officia elit tempor cupidatat amet. Aute exercitation occaecat occaecat irure pariatur deserunt ullamco cupidatat elit ullamco cillum officia excepteur.",
            "spans": []
          },
          {
            "type": "paragraph",
            "text": "Pariatur eu in excepteur aliqua aute dolore cillum.",
            "spans": []
          },
          {
            "type": "paragraph",
            "text": "Nisi aute aliqua dolor nisi. Duis commodo aliqua consequat officia culpa exercitation velit deserunt ipsum mollit eiusmod. Dolore proident nulla voluptate cupidatat ea irure est qui cillum.",
            "spans": []
          },
          {
            "type": "paragraph",
            "text": "Amet et nulla voluptate commodo velit labore. Deserunt elit ut et commodo qui cillum exercitation enim reprehenderit exercitation ullamco voluptate. Qui ut veniam cupidatat est quis officia velit amet adipisicing aliqua aute nulla aliquip.",
            "spans": []
          }
        ],
        "latestPostsLink": "111111",
        "latestPostsImage": {
          "dimensions": {
            "width": 900,
            "height": 500
          },
          "alt": null,
          "copyright": null,
          "url": "https://images.unsplash.com/photo-1607582278043-57198ac8da43"
        }
      }
    ],
    "primary": {},
    "slice_type": "latest_posts"
  },
  {
    "variation": "postsWithVideo",
    "version": "sktwi1xtmkfgx8626",
    "items": [
      {
        "latestPostsTitle": "without",
        "latestPostsText": [
          {
            "type": "paragraph",
            "text": "Deserunt sint sunt cillum aliquip duis voluptate mollit dolor id aliqua. Et eiusmod ullamco nisi eiusmod nulla nostrud ex fugiat ex commodo commodo do culpa Lorem adipisicing.",
            "spans": []
          }
        ],
        "latestPostsLink": "trick",
        "latestPostsImage": {
          "dimensions": {
            "width": 900,
            "height": 500
          },
          "alt": null,
          "copyright": null,
          "url": "https://images.unsplash.com/photo-1525547719571-a2d4ac8945e2"
        }
      }
    ],
    "primary": {},
    "slice_type": "latest_posts"
  }
]